MANIFEST.in
README.rst
VERSION
setup.py
templex/__init__.py
templex/core.py
templex/exceptions.py
templex.egg-info/PKG-INFO
templex.egg-info/SOURCES.txt
templex.egg-info/dependency_links.txt
templex.egg-info/not-zip-safe
templex.egg-info/top_level.txt