Metadata-Version: 1.1
Name: templex
Version: 0.2.0
Summary: Templated regular expressions
Home-page: https://github.com/crdoconnor/templex
Author: Colm O'Connor
Author-email: colm.oconnor.github@gmail.com
License: MIT
Keywords: regex
Platform: UNKNOWN
Classifier: Development Status :: 4 - Beta
Classifier: Intended Audience :: Developers
Classifier: License :: OSI Approved :: MIT License
Classifier: Topic :: Text Processing :: Markup
Classifier: Topic :: Software Development :: Libraries
Classifier: Natural Language :: English
Classifier: Programming Language :: Python :: 2
Classifier: Programming Language :: Python :: 2.6
Classifier: Programming Language :: Python :: 2.7
Classifier: Programming Language :: Python :: 3
Classifier: Programming Language :: Python :: 3.1
Classifier: Programming Language :: Python :: 3.2
Classifier: Programming Language :: Python :: 3.3
Classifier: Programming Language :: Python :: 3.4
Classifier: Programming Language :: Python :: 3.5
